hl/__init__.py
hl/hl.py
hl/hl_cli.py
hl-0.1.10.dist-info/METADATA
hl-0.1.10.dist-info/RECORD
hl-0.1.10.dist-info/WHEEL
hl-0.1.10.dist-info/entry_points.txt
hl-0.1.10.dist-info/top_level.txt
