Metadata-Version: 2.1
Name: hl
Version: 0.1.10
Summary: HL - Host List, a simple flexible fuzzy search/execute tool for lists of hosts
Home-page: https://github.com/pypa/example-project
Author: Dmitry Olshansky
Author-email: dmitry@olshansky.me
License: UNKNOWN
Platform: UNKNOWN
Classifier: Programming Language :: Python :: 3
Classifier: License :: OSI Approved :: MIT License
Classifier: Operating System :: OS Independent
